seaborn_extensions/__init__.py
seaborn_extensions/_types.py
seaborn_extensions/_utils.py
seaborn_extensions/_version.py
seaborn_extensions/annotated_clustermap.py
seaborn_extensions/py.typed
seaborn_extensions/rankplot.py
seaborn_extensions/swarmboxenplot.py
seaborn_extensions/volcano.py
seaborn_extensions-0.2.1.dist-info/METADATA
seaborn_extensions-0.2.1.dist-info/WHEEL
seaborn_extensions-0.2.1.dist-info/top_level.txt
seaborn_extensions-0.2.1.dist-info/RECORD
